postimg/__init__.py
postimg/postimg.py
postimg-2.1.data/scripts/postimg
postimg-2.1.dist-info/LICENSE
postimg-2.1.dist-info/METADATA
postimg-2.1.dist-info/WHEEL
postimg-2.1.dist-info/top_level.txt
postimg-2.1.dist-info/RECORD
